README.md
setup.py
libpythontools/__init__.py
libpythontools/github_api.py
libpythontools.egg-info/PKG-INFO
libpythontools.egg-info/SOURCES.txt
libpythontools.egg-info/dependency_links.txt
libpythontools.egg-info/not-zip-safe
libpythontools.egg-info/requires.txt
libpythontools.egg-info/top_level.txt
libpythontools/spam/__init__.py
libpythontools/spam/enviador_de_email.py
libpythontools/tests/__init__.py
libpythontools/tests/test_exemplo.py
libpythontools/tests/test_spam/__init__.py
libpythontools/tests/test_spam/test_enviador_de_email.py